{
  "create_response": {
    "status": "accepted",
    "tenant_id": "stock-market-decoder",
    "message": "Tenant creation started in the background. Use GET /tenants/infra/status?tenant_id=... to check progress."
  },
  "poll_response": {},
  "monitor_response": {
    "tenant_id": "stock-market-decoder",
    "knowledge_collection": {
      "row_count": 0,
      "dimensions": 1536
    },
    "memory_collection": {
      "row_count": 0,
      "dimensions": 0
    },
    "message": "Successfully retrieved tenant collection statistics"
  },
  "ingest_response": {
    "success": true,
    "message": "Knowledge uploaded successfully",
    "results": [
      {
        "source_id": "peloton_2020-12-21_8k",
        "filename": "peloton_2020-12-21_8k.md",
        "status": "queued",
        "error": null,
        "error_code": null
      },
      {
        "source_id": "peloton_2020-12-21_pr",
        "filename": "peloton_2020-12-21_pr.md",
        "status": "queued",
        "error": null,
        "error_code": null
      },
      {
        "source_id": "peloton_2021-08-26_8k",
        "filename": "peloton_2021-08-26_8k.md",
        "status": "queued",
        "error": null,
        "error_code": null
      },
      {
        "source_id": "peloton_2021-08-26_shareholder-letter",
        "filename": "peloton_2021-08-26_shareholder-letter.md",
        "status": "queued",
        "error": null,
        "error_code": null
      },
      {
        "source_id": "peloton_2022-02-05_8k",
        "filename": "peloton_2022-02-05_8k.md",
        "status": "queued",
        "error": null,
        "error_code": null
      },
      {
        "source_id": "peloton_2022-02-05_board-pr",
        "filename": "peloton_2022-02-05_board-pr.md",
        "status": "queued",
        "error": null,
        "error_code": null
      },
      {
        "source_id": "peloton_2022-02-08_8k",
        "filename": "peloton_2022-02-08_8k.md",
        "status": "queued",
        "error": null,
        "error_code": null
      },
      {
        "source_id": "peloton_2022-02-08_shareholder-letter",
        "filename": "peloton_2022-02-08_shareholder-letter.md",
        "status": "queued",
        "error": null,
        "error_code": null
      },
      {
        "source_id": "peloton_2022-02-08_restructuring-pr",
        "filename": "peloton_2022-02-08_restructuring-pr.md",
        "status": "queued",
        "error": null,
        "error_code": null
      },
      {
        "source_id": "peloton_2022-06-06_8k",
        "filename": "peloton_2022-06-06_8k.md",
        "status": "queued",
        "error": null,
        "error_code": null
      },
      {
        "source_id": "peloton_2022-06-06_pr",
        "filename": "peloton_2022-06-06_pr.md",
        "status": "queued",
        "error": null,
        "error_code": null
      },
      {
        "source_id": "peloton_2024-05-20_8k",
        "filename": "peloton_2024-05-20_8k.md",
        "status": "queued",
        "error": null,
        "error_code": null
      },
      {
        "source_id": "peloton_2024-05-20_pr",
        "filename": "peloton_2024-05-20_pr.md",
        "status": "queued",
        "error": null,
        "error_code": null
      }
    ],
    "success_count": 13,
    "failed_count": 0
  },
  "status_results": {
    "peloton_2020-12-21_pr": {
      "indexing_status": "timeout"
    },
    "peloton_2022-02-08_8k": {
      "indexing_status": "timeout"
    },
    "peloton_2022-02-08_shareholder-letter": {
      "indexing_status": "timeout"
    },
    "peloton_2022-02-08_restructuring-pr": {
      "indexing_status": "timeout"
    },
    "peloton_2022-02-05_8k": {
      "indexing_status": "timeout"
    },
    "peloton_2021-08-26_shareholder-letter": {
      "indexing_status": "timeout"
    },
    "peloton_2022-06-06_pr": {
      "indexing_status": "timeout"
    },
    "peloton_2021-08-26_8k": {
      "indexing_status": "timeout"
    },
    "peloton_2022-06-06_8k": {
      "indexing_status": "timeout"
    },
    "peloton_2020-12-21_8k": {
      "indexing_status": "timeout"
    },
    "peloton_2024-05-20_8k": {
      "indexing_status": "timeout"
    },
    "peloton_2022-02-05_board-pr": {
      "indexing_status": "timeout"
    },
    "peloton_2024-05-20_pr": {
      "indexing_status": "timeout"
    }
  },
  "recall_response": {
    "chunks": [],
    "sources": [],
    "graph_context": {
      "query_paths": [
        {
          "triplets": [
            {
              "source": {
                "name": "peloton",
                "type": "ORGANIZATION",
                "namespace": "organizations",
                "entity_id": "f25a0bb2f048a9d9cb72764d3a086f83",
                "identifier": "NASDAQ: PTON"
              },
              "relation": {
                "canonical_predicate": "entered into an agreement to acquire",
                "raw_predicate": "entered into an agreement to acquire",
                "context": "Peloton entered into an agreement to acquire Precor in a transaction valued at $420 million USD to establish a U.S. manufacturing footprint, enhance R&D capabilities, and accelerate growth of commercial verticals.",
                "confidence": 0.8,
                "temporal_details": "2020-12-21",
                "timestamp": "2026-07-12T01:19:44.814665",
                "relationship_id": "a129945b91e7bb820e9ddc3dac9ecaac",
                "chunk_id": "peloton_2020-12-21_pr_chunk_0000",
                "source_entity_id": "f25a0bb2f048a9d9cb72764d3a086f83",
                "target_entity_id": "8b4d74f8817024af9060741f7da759f1"
              },
              "target": {
                "name": "precor",
                "type": "ORGANIZATION",
                "namespace": "organizations",
                "entity_id": "8b4d74f8817024af9060741f7da759f1",
                "identifier": null
              }
            }
          ],
          "relevancy_score": 0.591832303366627,
          "combined_context": "Peloton entered into an agreement to acquire Precor in a transaction valued at $420 million USD to establish a U.S. manufacturing footprint, enhance R&D capabilities, and accelerate growth of commercial verticals. (Date/Time: 2020-12-21)",
          "group_id": "p_0",
          "source_chunk_ids": null
        },
        {
          "triplets": [
            {
              "source": {
                "name": "peloton",
                "type": "ORGANIZATION",
                "namespace": "organizations",
                "entity_id": "f25a0bb2f048a9d9cb72764d3a086f83",
                "identifier": "NASDAQ: PTON"
              },
              "relation": {
                "canonical_predicate": "reported revenue drivers",
                "raw_predicate": "reported revenue drivers",
                "context": "Peloton's Q2 2022 total revenue of $1,133.9 million was driven by higher Subscription revenue and contributions from Precor, though offset by a decline in Connected Fitness Product sales.",
                "confidence": 0.8,
                "temporal_details": "2022-02-08",
                "timestamp": "2026-07-12T01:19:44.814621",
                "relationship_id": "f04bf9af85e37e1e8f7cc64d57be8ea8",
                "chunk_id": "peloton_2022-02-08_shareholder-letter_chunk_0003",
                "source_entity_id": "f25a0bb2f048a9d9cb72764d3a086f83",
                "target_entity_id": "8b4d74f8817024af9060741f7da759f1"
              },
              "target": {
                "name": "precor",
                "type": "ORGANIZATION",
                "namespace": "organizations",
                "entity_id": "8b4d74f8817024af9060741f7da759f1",
                "identifier": null
              }
            }
          ],
          "relevancy_score": 0.46670540703029606,
          "combined_context": "Peloton's Q2 2022 total revenue of $1,133.9 million was driven by higher Subscription revenue and contributions from Precor, though offset by a decline in Connected Fitness Product sales. (Date/Time: 2022-02-08)",
          "group_id": "p_1",
          "source_chunk_ids": null
        }
      ],
      "chunk_relations": [],
      "chunk_id_to_group_ids": {},
      "synthesis_context": null
    },
    "additional_context": {}
  },
  "boolean_recall_response": {
    "chunks": [],
    "sources": [],
    "graph_context": {
      "query_paths": [],
      "chunk_relations": [],
      "chunk_id_to_group_ids": {},
      "synthesis_context": null
    },
    "additional_context": {}
  },
  "subtenant_test": {
    "ingest_response": {
      "success": true,
      "message": "Knowledge uploaded successfully",
      "results": [
        {
          "source_id": "subtenant_test_precor_doc",
          "filename": "peloton_2020-12-21_pr.md",
          "status": "queued",
          "error": null,
          "error_code": null
        }
      ],
      "success_count": 1,
      "failed_count": 0
    },
    "processing_status": {
      "subtenant_test_precor_doc": {
        "indexing_status": "timeout"
      }
    },
    "boolean_recall_response": {
      "chunks": [],
      "sources": [],
      "graph_context": {
        "query_paths": [],
        "chunk_relations": [],
        "chunk_id_to_group_ids": {},
        "synthesis_context": null
      },
      "additional_context": {}
    }
  }
}